{
      "items": [
        {"id":96881,"gems":[95347,76645]},
        {"id":96932,"gems":[76700,76700],"reforging":119},
        {"id":96698,"enchant":4806,"gems":[76672,76700],"reforging":147},
        {"id":96857,"enchant":4892,"gems":[76672],"reforging":147},
        {"id":96694,"enchant":4419,"gems":[76672,76700,76645],"reforging":117},
        {"id":96789,"randomSuffix":-339,"enchant":4414,"gems":[76700,0]},
        {"id":96695,"enchant":4433,"gems":[76672,0],"reforging":145,"tinker":4898},
        {"id":94999,"gems":[76645,76645,76700]},
        {"id":96697,"enchant":4826,"gems":[76700,76645],"reforging":147},
        {"id":96759,"enchant":4429,"gems":[76700],"reforging":119},
        {"id":95019,"gems":[76645],"reforging":140},
        {"id":95018,"gems":[76645],"reforging":119},
        {"id":96827,"reforging":154},
        {"id":96785,"reforging":140},
        {"id":96890,"enchant":4442,"gems":[76672,76700]},
        {"id":96910,"enchant":4434,"gems":[76672],"reforging":117}
      ]
    }
